notbadai_inline_completion/__init__.py
notbadai_inline_completion/common/__init__.py
notbadai_inline_completion/common/diff.py
notbadai_inline_completion/common/file_type.py
notbadai_inline_completion/common/formatting.py
notbadai_inline_completion/common/git_client.py
notbadai_inline_completion/common/llm.py
notbadai_inline_completion/common/models.py
notbadai_inline_completion/common/prompt.py
notbadai_inline_completion/common/settings.py
notbadai_inline_completion/common/terminal.py
notbadai_inline_completion/common/utils.py
notbadai_inline_completion-0.1.1.dist-info/METADATA
notbadai_inline_completion-0.1.1.dist-info/WHEEL
notbadai_inline_completion-0.1.1.dist-info/top_level.txt
notbadai_inline_completion-0.1.1.dist-info/RECORD
