Metadata-Version: 2.4
Name: notbadai_inline_completion
Version: 0.1.1
Summary: An intelligent programming assistant powered by AI
Home-page: https://github.com/notbadai/extensions
Author: NotBadAI Team
Author-email: contact@notbad.ai
Classifier: Programming Language :: Python :: 3
Classifier: Intended Audience :: Developers
Classifier: License :: OSI Approved :: MIT License
Classifier: Topic :: Software Development
Classifier: Topic :: Software Development :: Libraries
Classifier: Topic :: Software Development :: Libraries :: Python Modules
Requires-Python: >=3.8
Requires-Dist: notbadai_ide
Requires-Dist: labml
Requires-Dist: requests
Requires-Dist: openai
Dynamic: author
Dynamic: author-email
Dynamic: classifier
Dynamic: description-content-type
Dynamic: home-page
Dynamic: requires-dist
Dynamic: requires-python
Dynamic: summary
